yawgbot/__init__.py
yawgbot/app.py
yawgbot/bot.py
yawgbot/index.html
yawgbot/listing.py
yawgbot/pluginBase.py
yawgbot/plugins/__init__.py
yawgbot/plugins/wg-gesucht.py
yawgbot-0.0.7.dist-info/METADATA
yawgbot-0.0.7.dist-info/WHEEL
yawgbot-0.0.7.dist-info/entry_points.txt
yawgbot-0.0.7.dist-info/licenses/LICENSE.md
yawgbot-0.0.7.dist-info/RECORD
