Metadata-Version: 2.1
Name: yawgbot
Version: 0.0.7
Summary: yawgbot - yet another wg bot
Project-URL: Homepage, https://github.com/rcastellotti/yawgbot
Project-URL: Bug Tracker, https://github.com/rcastellotti/yawgbot/issues
Author-email: Roberto Castellotti <me@rcastellotti.dev>
License: Copyright 2022 Roberto Castellotti
License-File: LICENSE.md
Classifier: License :: OSI Approved :: MIT License
Classifier: Operating System :: OS Independent
Classifier: Programming Language :: Python :: 3
Requires-Python: >=3.7
Requires-Dist: beautifulsoup4==4.11.1
Requires-Dist: certifi==2022.6.15
Requires-Dist: charset-normalizer==2.1.1
Requires-Dist: click==8.1.3
Requires-Dist: flask==2.2.2
Requires-Dist: greenlet==1.1.3
Requires-Dist: idna==3.3
Requires-Dist: itsdangerous==2.1.2
Requires-Dist: jinja2==3.1.2
Requires-Dist: markupsafe==2.1.1
Requires-Dist: platformdirs==2.5.2
Requires-Dist: python-dotenv==0.21.0
Requires-Dist: pyyaml==6.0
Requires-Dist: requests==2.28.1
Requires-Dist: soupsieve==2.3.2.post1
Requires-Dist: sqlalchemy-utils==0.38.3
Requires-Dist: sqlalchemy==1.4.41
Requires-Dist: urllib3==1.26.12
Requires-Dist: werkzeug==2.2.2
